skyscanner_referrals/__init__.py
skyscanner_referrals/sdk.py
skyscanner_referrals/hooks/__init__.py
skyscanner_referrals/hooks/hook.py
skyscanner_referrals/models/__init__.py
skyscanner_referrals/models/base.py
skyscanner_referrals/models/utils/cast_models.py
skyscanner_referrals/models/utils/json_map.py
skyscanner_referrals/net/__init__.py
skyscanner_referrals/net/environment/__init__.py
skyscanner_referrals/net/environment/environment.py
skyscanner_referrals/net/headers/__init__.py
skyscanner_referrals/net/headers/api_key_auth.py
skyscanner_referrals/net/headers/base_header.py
skyscanner_referrals/net/request_chain/__init__.py
skyscanner_referrals/net/request_chain/request_chain.py
skyscanner_referrals/net/request_chain/handlers/__init__.py
skyscanner_referrals/net/request_chain/handlers/base_handler.py
skyscanner_referrals/net/request_chain/handlers/hook_handler.py
skyscanner_referrals/net/request_chain/handlers/http_handler.py
skyscanner_referrals/net/request_chain/handlers/retry_handler.py
skyscanner_referrals/net/transport/__init__.py
skyscanner_referrals/net/transport/request.py
skyscanner_referrals/net/transport/request_error.py
skyscanner_referrals/net/transport/response.py
skyscanner_referrals/net/transport/serializer.py
skyscanner_referrals/net/transport/utils.py
skyscanner_referrals/services/__init__.py
skyscanner_referrals/services/car_hire.py
skyscanner_referrals/services/flights.py
skyscanner_referrals/services/hotels.py
skyscanner_referrals/services/utils/base_service.py
skyscanner_referrals/services/utils/default_headers.py
skyscanner_referrals/services/utils/validator.py
skyscanner_referrals-1.0.0.dist-info/LICENSE
skyscanner_referrals-1.0.0.dist-info/METADATA
skyscanner_referrals-1.0.0.dist-info/WHEEL
skyscanner_referrals-1.0.0.dist-info/top_level.txt
skyscanner_referrals-1.0.0.dist-info/RECORD
